<?xml version="1.0" encoding="UTF-8"?>
<record_update table="x_qune_da_error_code">
    <x_qune_da_error_code action="INSERT_OR_UPDATE">
        <active>true</active>
        <discovery_phase>phase_4</discovery_phase>
        <error_code>P4.WMI.01</error_code>
        <remediation>Troubleshooting steps should be followed in the order given below.&#13;
1. Further troubleshoot error to determine which commands do not have permissions.&#13;
2. Work with Server Support Team / Application Support Team to grant access to ServiceNow Service ID to execute those commands on the Device, if specific attributes returned by those commands are in scope of the CMDB Design.</remediation>
        <root_cause>ServiceNow Service ID does not have permissions to execute specific WMI commands configured in the Probe.</root_cause>
        <sys_class_name>x_qune_da_error_code</sys_class_name>
        <sys_created_by>admin</sys_created_by>
        <sys_created_on>2017-08-08 21:26:29</sys_created_on>
        <sys_customer_update>true</sys_customer_update>
        <sys_id>e3477c14db688300799d540adc96194d</sys_id>
        <sys_mod_count>0</sys_mod_count>
        <sys_name>P4.WMI.01</sys_name>
        <sys_package display_value="Discovery Admin" source="x_qune_da">6a926b7edb144300799d540adc961933</sys_package>
        <sys_policy/>
        <sys_replace_on_upgrade>false</sys_replace_on_upgrade>
        <sys_scope display_value="Discovery Admin">6a926b7edb144300799d540adc961933</sys_scope>
        <sys_update_name>x_qune_da_error_code_e3477c14db688300799d540adc96194d</sys_update_name>
        <sys_updated_by>admin</sys_updated_by>
        <sys_updated_on>2017-08-08 21:26:29</sys_updated_on>
        <team_responsible>Device Support Team</team_responsible>
    </x_qune_da_error_code>
</record_update>
